django_pymssql-1.7.1.dist-info/DESCRIPTION.rst
django_pymssql-1.7.1.dist-info/METADATA
django_pymssql-1.7.1.dist-info/RECORD
django_pymssql-1.7.1.dist-info/WHEEL
django_pymssql-1.7.1.dist-info/metadata.json
django_pymssql-1.7.1.dist-info/pbr.json
django_pymssql-1.7.1.dist-info/top_level.txt
sqlserver_pymssql/__init__.py
sqlserver_pymssql/base.py
sqlserver_pymssql/compiler.py
