Metadata-Version: 2.0
Name: django-pymssql
Version: 1.7.1
Summary: Django database backend for Microsoft SQL Server that works on non-Windows systems.
Home-page: https://github.com/aaugustin/django-pymssql
Author: Aymeric Augustin
Author-email: aymeric.augustin@m4x.org
License: BSD
Download-URL: http://pypi.python.org/pypi/django-pymssql
Platform: all
Classifier: Development Status :: 4 - Beta
Classifier: Environment :: Web Environment
Classifier: Framework :: Django
Classifier: Framework :: Django :: 1.7
Classifier: Intended Audience :: Developers
Classifier: License :: OSI Approved :: BSD License
Classifier: Operating System :: OS Independent
Classifier: Programming Language :: Python
Classifier: Programming Language :: Python :: 2
Classifier: Programming Language :: Python :: 2.7
Classifier: Programming Language :: Python :: 3
Classifier: Programming Language :: Python :: 3.4
Requires-Dist: Django
Requires-Dist: django-mssql
Requires-Dist: pymssql
